biosimulators_cbmpy/__init__.py
biosimulators_cbmpy/__main__.py
biosimulators_cbmpy/_version.py
biosimulators_cbmpy/core.py
biosimulators_cbmpy/data_model.py
biosimulators_cbmpy/utils.py
biosimulators_cbmpy-0.1.15.dist-info/LICENSE
biosimulators_cbmpy-0.1.15.dist-info/METADATA
biosimulators_cbmpy-0.1.15.dist-info/WHEEL
biosimulators_cbmpy-0.1.15.dist-info/entry_points.txt
biosimulators_cbmpy-0.1.15.dist-info/top_level.txt
biosimulators_cbmpy-0.1.15.dist-info/RECORD
