Metadata-Version: 2.1
Name: biosimulators-cbmpy
Version: 0.1.15
Summary: BioSimulators-compliant command-line interface to the CBMPy simulation program <http://cbmpy.sourceforge.net/>.
Home-page: https://github.com/biosimulators/Biosimulators_CBMPy>
Download-URL: https://github.com/biosimulators/Biosimulators_CBMPy
Author: Center for Reproducible Biomedical Modeling
Author-email: info@biosimulators.org
License: MIT
Keywords: BioSimulators,systems biology,computational biology,mathematical model,kinetic model,simulation,SBML,SED-ML,COMBINE,OMEX
Platform: UNKNOWN
Classifier: Development Status :: 3 - Alpha
Classifier: Intended Audience :: Science/Research
Classifier: License :: OSI Approved :: MIT License
Classifier: Topic :: Scientific/Engineering :: Bio-Informatics
License-File: LICENSE
Requires-Dist: biosimulators-utils[logging] (>=0.1.162)
Requires-Dist: cbmpy (<=0.7.25)
Requires-Dist: glpk
Requires-Dist: kisao
Requires-Dist: lxml
Requires-Dist: numpy
Requires-Dist: python-libsbml
Requires-Dist: sympy (!=1.8,!=1.9)
Provides-Extra: all
Requires-Dist: biosimulators-utils[containers] ; extra == 'all'
Requires-Dist: python-dateutil ; extra == 'all'
Provides-Extra: docs
Provides-Extra: tests
Requires-Dist: biosimulators-utils[containers] ; extra == 'tests'
Requires-Dist: python-dateutil ; extra == 'tests'
